catchpoint/__init__.py
catchpoint/_version.py
catchpoint/catchpoint_agent.py
catchpoint/compat.py
catchpoint/composite.py
catchpoint/constants.py
catchpoint/encoder.py
catchpoint/handler.py
catchpoint/reporter.py
catchpoint/serializable.py
catchpoint/timeout.py
catchpoint/utils.py
catchpoint/application/__init__.py
catchpoint/application/application_info.py
catchpoint/application/application_info_provider.py
catchpoint/application/global_application_info_provider.py
catchpoint/config/__init__.py
catchpoint/config/config_metadata.py
catchpoint/config/config_names.py
catchpoint/config/config_provider.py
catchpoint/context/__init__.py
catchpoint/context/context_provider.py
catchpoint/context/execution_context.py
catchpoint/context/execution_context_manager.py
catchpoint/context/global_execution_context_provider.py
catchpoint/context/plugin_context.py
catchpoint/context/tracing_execution_context_provider.py
catchpoint/debug/__init__.py
catchpoint/debug/bridge.py
catchpoint/integrations/__init__.py
catchpoint/integrations/base_integration.py
catchpoint/integrations/botocore.py
catchpoint/integrations/django.py
catchpoint/integrations/elasticsearch.py
catchpoint/integrations/mongodb.py
catchpoint/integrations/mysql.py
catchpoint/integrations/postgre.py
catchpoint/integrations/rdb_base.py
catchpoint/integrations/redis.py
catchpoint/integrations/requests.py
catchpoint/integrations/sqlalchemy.py
catchpoint/integrations/sqlite3.py
catchpoint/integrations/aiohttp/__init__.py
catchpoint/integrations/aiohttp/client.py
catchpoint/integrations/handler_wrappers/__init__.py
catchpoint/integrations/handler_wrappers/chalice.py
catchpoint/integrations/modules/__init__.py
catchpoint/integrations/modules/aiohttp.py
catchpoint/integrations/modules/botocore.py
catchpoint/integrations/modules/db.py
catchpoint/integrations/modules/django.py
catchpoint/integrations/modules/elasticsearch.py
catchpoint/integrations/modules/fastapi.py
catchpoint/integrations/modules/flask.py
thundra-3.0.10.dist-info/LICENSE
thundra-3.0.10.dist-info/METADATA
thundra-3.0.10.dist-info/WHEEL
thundra-3.0.10.dist-info/top_level.txt
thundra-3.0.10.dist-info/zip-safe
thundra-3.0.10.dist-info/RECORD
