Metadata-Version: 2.1
Name: thundra
Version: 3.0.10
Summary: Catchpoint Python agent
Home-page: https://github.com/thundra-io/cp-trace-python
Author: Catchpoint
Author-email: python@catchpoint.io
Classifier: Development Status :: 5 - Production/Stable
Classifier: Intended Audience :: Developers
Classifier: License :: OSI Approved :: Apache Software License
Classifier: Programming Language :: Python
Classifier: Programming Language :: Python :: 2
Classifier: Programming Language :: Python :: 2.7
Classifier: Programming Language :: Python :: 3
Classifier: Programming Language :: Python :: 3.6
Classifier: Programming Language :: Python :: 3.7
Classifier: Programming Language :: Python :: 3.8
Requires-Python: >=2.7, !=3.0.*, !=3.1.*, !=3.2.*, !=3.3.*, !=3.4.*, !=3.5.*
License-File: LICENSE
Requires-Dist: requests (>=2.16.0)
Requires-Dist: opentracing (>=2.0)
Requires-Dist: wrapt (>=1.10.11)
Requires-Dist: simplejson
Requires-Dist: enum-compat
Requires-Dist: pep440-rs
Requires-Dist: jsonpickle (==1.3)
Requires-Dist: websocket-client
Requires-Dist: python-dateutil
Requires-Dist: GitPython (>=3.1.18)
Requires-Dist: fastcounter (>=1.1.0)
Requires-Dist: pympler
